mcelfish/__init__.py
mcelfish/carle_strub.py
mcelfish/generate_sampling.py
mcelfish/plot_beta.py
mcelfish/removal_sampling.py
mcelfish/testdata.py
mcelfish-0.0.5.dist-info/LICENSE
mcelfish-0.0.5.dist-info/METADATA
mcelfish-0.0.5.dist-info/WHEEL
mcelfish-0.0.5.dist-info/entry_points.txt
mcelfish-0.0.5.dist-info/top_level.txt
mcelfish-0.0.5.dist-info/RECORD
